{
  "claims": [
    {
      "id": "claim_001",
      "section": "Identity of Target System",
      "statement": "ELI is a framework for producing justified, auditable claims from signed artifacts by defining JSON schema contracts and validation logic for its outputs.",
      "confidence": 1.0,
      "evidence": [
        {
          "path": "README.md",
          "line_start": 1,
          "line_end": 4,
          "display": "README.md:1-4",
          "snippet_hash": "38bce6d78e2d",
          "snippet_hash_verified": true
        }
      ],
      "status": "evidenced"
    },
    {
      "id": "claim_002",
      "section": "Identity of Target System",
      "statement": "ELI separates the concerns of cryptographic proof from inference and does not perform signing or manage evidence directly.",
      "confidence": 1.0,
      "evidence": [
        {
          "path": "README.md",
          "line_start": 5,
          "line_end": 10,
          "display": "README.md:5-10",
          "snippet_hash": "23333730b527",
          "snippet_hash_verified": true
        },
        {
          "path": "references/halo-integration.md",
          "line_start": 8,
          "line_end": 9,
          "display": "references/halo-integration.md:8-9",
          "snippet_hash": "3c582adb5ce3",
          "snippet_hash_verified": true
        }
      ],
      "status": "evidenced"
    },
    {
      "id": "claim_003",
      "section": "Identity of Target System",
      "statement": "The repository is an early-stage scaffold and is not intended for production use.",
      "confidence": 1.0,
      "evidence": [
        {
          "path": "README.md",
          "line_start": 36,
          "line_end": 36,
          "display": "README.md:36",
          "snippet_hash": "33ec38cb52fd",
          "snippet_hash_verified": true
        },
        {
          "path": "SECURITY.md",
          "line_start": 24,
          "line_end": 24,
          "display": "SECURITY.md:24",
          "snippet_hash": "f73a1073763a",
          "snippet_hash_verified": true
        }
      ],
      "status": "evidenced"
    },
    {
      "id": "claim_004",
      "section": "Identity of Target System",
      "statement": "ELI does not execute cryptographic signing, store raw evidence, or manage keys.",
      "confidence": 1.0,
      "evidence": [
        {
          "path": "EVIDENCE.md",
          "line_start": 3,
          "line_end": 3,
          "display": "EVIDENCE.md:3",
          "snippet_hash": "d4571bdd157a",
          "snippet_hash_verified": true
        },
        {
          "path": "references/halo-integration.md",
          "line_start": 8,
          "line_end": 9,
          "display": "references/halo-integration.md:8-9",
          "snippet_hash": "3c582adb5ce3",
          "snippet_hash_verified": true
        }
      ],
      "status": "evidenced"
    },
    {
      "id": "claim_005",
      "section": "Identity of Target System",
      "statement": "ELI is not a universal truth system, a cryptographic substitute, or a self-verifying claim engine.",
      "confidence": 1.0,
      "evidence": [
        {
          "path": "CLAIM.md",
          "line_start": 15,
          "line_end": 16,
          "display": "CLAIM.md:15-16",
          "snippet_hash": "99c2d054cc23",
          "snippet_hash_verified": true
        },
        {
          "path": "EVIDENCE.md",
          "line_start": 32,
          "line_end": 33,
          "display": "EVIDENCE.md:32-33",
          "snippet_hash": "b265c71bd30d",
          "snippet_hash_verified": true
        }
      ],
      "status": "evidenced"
    },
    {
      "id": "claim_006",
      "section": "Identity of Target System",
      "statement": "Not a production-ready pipeline or artifact deployer.",
      "confidence": 1.0,
      "evidence": [
        {
          "path": "SECURITY.md",
          "line_start": 24,
          "line_end": 24,
          "display": "SECURITY.md:24",
          "snippet_hash": "f73a1073763a",
          "snippet_hash_verified": true
        }
      ],
      "status": "evidenced"
    },
    {
      "id": "claim_007",
      "section": "Purpose & Jobs-to-be-done",
      "statement": "ELI aims to define and validate auditable claims about digital artifacts using a formal schema.",
      "confidence": 1.0,
      "evidence": [
        {
          "path": "README.md",
          "line_start": 1,
          "line_end": 4,
          "display": "README.md:1-4",
          "snippet_hash": "38bce6d78e2d",
          "snippet_hash_verified": true
        }
      ],
      "status": "evidenced"
    },
    {
      "id": "claim_008",
      "section": "Purpose & Jobs-to-be-done",
      "statement": "ELI enforces the separation of signed evidence from inference/claims, improving auditability and clarity over what is proven versus inferred.",
      "confidence": 1.0,
      "evidence": [
        {
          "path": "README.md",
          "line_start": 6,
          "line_end": 7,
          "display": "README.md:6-7",
          "snippet_hash": "1dec6584a3d1",
          "snippet_hash_verified": true
        },
        {
          "path": "EVIDENCE.md",
          "line_start": 3,
          "line_end": 4,
          "display": "EVIDENCE.md:3-4",
          "snippet_hash": "d4571bdd157a",
          "snippet_hash_verified": true
        }
      ],
      "status": "evidenced"
    },
    {
      "id": "claim_009",
      "section": "Purpose & Jobs-to-be-done",
      "statement": "ELI is designed to interoperate with external systems for signing and receipts, such as HALO-RECEIPTS.",
      "confidence": 1.0,
      "evidence": [
        {
          "path": "README.md",
          "line_start": 9,
          "line_end": 10,
          "display": "README.md:9-10",
          "snippet_hash": "0735400dcd7c",
          "snippet_hash_verified": true
        },
        {
          "path": "references/halo-integration.md",
          "line_start": 10,
          "line_end": 11,
          "display": "references/halo-integration.md:10-11",
          "snippet_hash": "dca23f8f2689",
          "snippet_hash_verified": true
        }
      ],
      "status": "evidenced"
    },
    {
      "id": "claim_010",
      "section": "Purpose & Jobs-to-be-done",
      "statement": "ELI provides a schema validator that enables checking of ELI output files for conformance to the defined contract.",
      "confidence": 1.0,
      "evidence": [
        {
          "path": "README.md",
          "line_start": 20,
          "line_end": 20,
          "display": "README.md:20",
          "snippet_hash": "f8e4d31b7491",
          "snippet_hash_verified": true
        },
        {
          "path": "validate-schema.js",
          "line_start": 101,
          "line_end": 149,
          "display": "validate-schema.js:101-149",
          "snippet_hash": "ccdb8daf830c",
          "snippet_hash_verified": true
        }
      ],
      "status": "evidenced"
    },
    {
      "id": "claim_011",
      "section": "Capability Map",
      "statement": "The system validates ELI output artifacts (JSON) against the defined schema.",
      "confidence": 1.0,
      "evidence": [
        {
          "path": "validate-schema.js",
          "line_start": 6,
          "line_end": 99,
          "display": "validate-schema.js:6-99",
          "snippet_hash": "787b5c101168",
          "snippet_hash_verified": true
        },
        {
          "path": "contracts/eli-output.schema.json",
          "line_start": 1,
          "line_end": 157,
          "display": "contracts/eli-output.schema.json:1-157",
          "snippet_hash": "021fb596db81",
          "snippet_hash_verified": true
        }
      ],
      "status": "evidenced"
    },
    {
      "id": "claim_012",
      "section": "Capability Map",
      "statement": "Validation results including errors and sample field previews are printed by the validator.",
      "confidence": 1.0,
      "evidence": [
        {
          "path": "validate-schema.js",
          "line_start": 123,
          "line_end": 144,
          "display": "validate-schema.js:123-144",
          "snippet_hash": "51aa490b21c4",
          "snippet_hash_verified": true
        }
      ],
      "status": "evidenced"
    },
    {
      "id": "claim_013",
      "section": "Capability Map",
      "statement": "ELI supports both local validation and Replit-based ('click Run') schema validation.",
      "confidence": 1.0,
      "evidence": [
        {
          "path": "README.md",
          "line_start": 14,
          "line_end": 19,
          "display": "README.md:14-19",
          "snippet_hash": "3095db2ec112",
          "snippet_hash_verified": true
        },
        {
          "path": ".replit",
          "line_start": 1,
          "line_end": 1,
          "display": ".replit:1",
          "snippet_hash": "eb5b96f312a1",
          "snippet_hash_verified": true
        }
      ],
      "status": "evidenced"
    },
    {
      "id": "claim_014",
      "section": "Capability Map",
      "statement": "ELI can be executed with Node.js version 20+ directly using the command 'node validate-schema.js'.",
      "confidence": 1.0,
      "evidence": [
        {
          "path": "README.md",
          "line_start": 27,
          "line_end": 27,
          "display": "README.md:27",
          "snippet_hash": "552aa2a53cfa",
          "snippet_hash_verified": true
        },
        {
          "path": "replit.nix",
          "line_start": 3,
          "line_end": 3,
          "display": "replit.nix:3",
          "snippet_hash": "b6d70b4bbe78",
          "snippet_hash_verified": true
        }
      ],
      "status": "evidenced"
    },
    {
      "id": "claim_015",
      "section": "Capability Map",
      "statement": "Strict schema conformance is enforced, including required fields and prohibition of additional properties.",
      "confidence": 1.0,
      "evidence": [
        {
          "path": "contracts/eli-output.schema.json",
          "line_start": 6,
          "line_end": 6,
          "display": "contracts/eli-output.schema.json:6",
          "snippet_hash": "caf6261bd512",
          "snippet_hash_verified": true
        },
        {
          "path": "validate-schema.js",
          "line_start": 10,
          "line_end": 94,
          "display": "validate-schema.js:10-94",
          "snippet_hash": "58f9846ee46c",
          "snippet_hash_verified": true
        }
      ],
      "status": "evidenced"
    },
    {
      "id": "claim_016",
      "section": "Architecture Snapshot",
      "statement": "The schema validator loads both schema and sample output dynamically and performs validation in-process, without external libraries.",
      "confidence": 1.0,
      "evidence": [
        {
          "path": "validate-schema.js",
          "line_start": 106,
          "line_end": 115,
          "display": "validate-schema.js:106-115",
          "snippet_hash": "2ede294108f0",
          "snippet_hash_verified": true
        }
      ],
      "status": "evidenced"
    },
    {
      "id": "claim_017",
      "section": "Architecture Snapshot",
      "statement": "Network operations, cryptographic operations, artifact signing, and key management are explicitely out of ELI's scope.",
      "confidence": 1.0,
      "evidence": [
        {
          "path": "EVIDENCE.md",
          "line_start": 3,
          "line_end": 3,
          "display": "EVIDENCE.md:3",
          "snippet_hash": "d4571bdd157a",
          "snippet_hash_verified": true
        },
        {
          "path": "references/halo-integration.md",
          "line_start": 8,
          "line_end": 11,
          "display": "references/halo-integration.md:8-11",
          "snippet_hash": "3c582adb5ce3",
          "snippet_hash_verified": true
        }
      ],
      "status": "evidenced"
    },
    {
      "id": "claim_018",
      "section": "How to Use the Target System",
      "statement": "The only software dependency required for validating artifacts is Node.js 20+; jq is listed for possible future scripts but is not required for validation.",
      "confidence": 1.0,
      "evidence": [
        {
          "path": "replit.nix",
          "line_start": 3,
          "line_end": 4,
          "display": "replit.nix:3-4",
          "snippet_hash": "b6d70b4bbe78",
          "snippet_hash_verified": true
        },
        {
          "path": "validate-schema.js",
          "line_start": 3,
          "line_end": 149,
          "display": "validate-schema.js:3-149",
          "snippet_hash": "24133e8118fe",
          "snippet_hash_verified": true
        }
      ],
      "status": "evidenced"
    },
    {
      "id": "claim_019",
      "section": "How to Use the Target System",
      "statement": "On Replit, all dependencies are pre-installed, and running the validator is triggered via the Run button.",
      "confidence": 1.0,
      "evidence": [
        {
          "path": "replit.nix",
          "line_start": 3,
          "line_end": 4,
          "display": "replit.nix:3-4",
          "snippet_hash": "b6d70b4bbe78",
          "snippet_hash_verified": true
        },
        {
          "path": "README.md",
          "line_start": 16,
          "line_end": 19,
          "display": "README.md:16-19",
          "snippet_hash": "ca45a45e1fb7",
          "snippet_hash_verified": true
        },
        {
          "path": ".replit",
          "line_start": 1,
          "line_end": 1,
          "display": ".replit:1",
          "snippet_hash": "eb5b96f312a1",
          "snippet_hash_verified": true
        }
      ],
      "status": "evidenced"
    },
    {
      "id": "claim_020",
      "section": "How to Use the Target System",
      "statement": "Validator script outputs '\u2713 Validation PASSED' if the sample output is schema-conformant, or lists errors and exits non-zero if it is not.",
      "confidence": 1.0,
      "evidence": [
        {
          "path": "validate-schema.js",
          "line_start": 124,
          "line_end": 135,
          "display": "validate-schema.js:124-135",
          "snippet_hash": "fd53cd7ba83c",
          "snippet_hash_verified": true
        }
      ],
      "status": "evidenced"
    },
    {
      "id": "claim_021",
      "section": "Integration Surface",
      "statement": "ELI exposes no APIs (REST, GraphQL, RPC), SDKs, or webhooks\u2014its only integration point is output artifacts in JSON.",
      "confidence": 1.0,
      "evidence": [
        {
          "path": "contracts/eli-output.schema.json",
          "line_start": 1,
          "line_end": 157,
          "display": "contracts/eli-output.schema.json:1-157",
          "snippet_hash": "021fb596db81",
          "snippet_hash_verified": true
        },
        {
          "path": "examples/eli-output.sample.json",
          "line_start": 1,
          "line_end": 56,
          "display": "examples/eli-output.sample.json:1-56",
          "snippet_hash": "021fb596db81",
          "snippet_hash_verified": true
        }
      ],
      "status": "evidenced"
    },
    {
      "id": "claim_022",
      "section": "Integration Surface",
      "statement": "ELI output JSON artifacts include fields designed for referencing evidence and signature objects, facilitating integration with systems like HALO-RECEIPTS.",
      "confidence": 1.0,
      "evidence": [
        {
          "path": "references/halo-integration.md",
          "line_start": 3,
          "line_end": 12,
          "display": "references/halo-integration.md:3-12",
          "snippet_hash": "8f74b44878df",
          "snippet_hash_verified": true
        }
      ],
      "status": "evidenced"
    },
    {
      "id": "claim_023",
      "section": "Data & Security Posture",
      "statement": "ELI handles only non-sensitive JSON schema and user-supplied output files, with no secrets or sensitive information processed.",
      "confidence": 1.0,
      "evidence": [
        {
          "path": "examples/eli-output.sample.json",
          "line_start": 1,
          "line_end": 56,
          "display": "examples/eli-output.sample.json:1-56",
          "snippet_hash": "021fb596db81",
          "snippet_hash_verified": true
        }
      ],
      "status": "evidenced"
    },
    {
      "id": "claim_024",
      "section": "Data & Security Posture",
      "statement": "ELI performs no encryption or cryptographic operations in validation or storage.",
      "confidence": 1.0,
      "evidence": [
        {
          "path": "EVIDENCE.md",
          "line_start": 3,
          "line_end": 3,
          "display": "EVIDENCE.md:3",
          "snippet_hash": "d4571bdd157a",
          "snippet_hash_verified": true
        },
        {
          "path": "validate-schema.js",
          "line_start": 3,
          "line_end": 149,
          "display": "validate-schema.js:3-149",
          "snippet_hash": "24133e8118fe",
          "snippet_hash_verified": true
        }
      ],
      "status": "evidenced"
    },
    {
      "id": "claim_025",
      "section": "Data & Security Posture",
      "statement": "No authentication, secret management, or secret material is part of ELI's operation.",
      "confidence": 1.0,
      "evidence": [
        {
          "path": "validate-schema.js",
          "line_start": 3,
          "line_end": 149,
          "display": "validate-schema.js:3-149",
          "snippet_hash": "24133e8118fe",
          "snippet_hash_verified": true
        }
      ],
      "status": "evidenced"
    },
    {
      "id": "claim_026",
      "section": "Data & Security Posture",
      "statement": "Security issues may be reported by email, but no security guarantees are provided for the code.",
      "confidence": 1.0,
      "evidence": [
        {
          "path": "SECURITY.md",
          "line_start": 13,
          "line_end": 13,
          "display": "SECURITY.md:13",
          "snippet_hash": "0d3b5bfae180",
          "snippet_hash_verified": true
        },
        {
          "path": "SECURITY.md",
          "line_start": 24,
          "line_end": 24,
          "display": "SECURITY.md:24",
          "snippet_hash": "f73a1073763a",
          "snippet_hash_verified": true
        }
      ],
      "status": "evidenced"
    },
    {
      "id": "claim_027",
      "section": "Operational Reality",
      "statement": "ELI has no background processes, servers, or uptime requirement\u2014operations are limited to CLI invocation of schema validation.",
      "confidence": 1.0,
      "evidence": [
        {
          "path": "validate-schema.js",
          "line_start": 1,
          "line_end": 149,
          "display": "validate-schema.js:1-149",
          "snippet_hash": "4949218de757",
          "snippet_hash_verified": true
        },
        {
          "path": "README.md",
          "line_start": 27,
          "line_end": 27,
          "display": "README.md:27",
          "snippet_hash": "552aa2a53cfa",
          "snippet_hash_verified": true
        }
      ],
      "status": "evidenced"
    },
    {
      "id": "claim_028",
      "section": "Operational Reality",
      "statement": "ELI has no dependency on external libraries or state persistence\u2014all validation logic and data remain local and ephemeral.",
      "confidence": 1.0,
      "evidence": [
        {
          "path": "validate-schema.js",
          "line_start": 3,
          "line_end": 149,
          "display": "validate-schema.js:3-149",
          "snippet_hash": "24133e8118fe",
          "snippet_hash_verified": true
        }
      ],
      "status": "evidenced"
    },
    {
      "id": "claim_029",
      "section": "Maintainability & Change Risk",
      "statement": "Schema evolution is the major risk; consumers and validators must be updated in lockstep with schema changes.",
      "confidence": 1.0,
      "evidence": [
        {
          "path": "contracts/eli-output.schema.json",
          "line_start": 1,
          "line_end": 157,
          "display": "contracts/eli-output.schema.json:1-157",
          "snippet_hash": "021fb596db81",
          "snippet_hash_verified": true
        },
        {
          "path": "examples/eli-output.sample.json",
          "line_start": 1,
          "line_end": 56,
          "display": "examples/eli-output.sample.json:1-56",
          "snippet_hash": "021fb596db81",
          "snippet_hash_verified": true
        }
      ],
      "status": "evidenced"
    },
    {
      "id": "claim_030",
      "section": "Maintainability & Change Risk",
      "statement": "Validator logic is hand-rolled and simple, but will require code updates for new JSON schema drafts or rules, since there is no external validation library.",
      "confidence": 1.0,
      "evidence": [
        {
          "path": "validate-schema.js",
          "line_start": 6,
          "line_end": 99,
          "display": "validate-schema.js:6-99",
          "snippet_hash": "787b5c101168",
          "snippet_hash_verified": true
        }
      ],
      "status": "evidenced"
    }
  ],
  "mode": "github",
  "run_id": "f052d0f706ba",
  "is_replit": false
}